longport/__init__.py
longport/longport.cpython-312-aarch64-linux-gnu.so
longport/openapi.py
longport/openapi.pyi
longport/py.typed
longport-3.0.21.dist-info/METADATA
longport-3.0.21.dist-info/WHEEL
longport-3.0.21.dist-info/RECORD
