Metadata-Version: 2.4
Name: longport
Version: 3.0.21
Classifier: Development Status :: 3 - Alpha
Classifier: Intended Audience :: Developers
Classifier: Topic :: Office/Business :: Financial
Classifier: Programming Language :: Rust
Classifier: Programming Language :: Python :: Implementation :: CPython
Summary: A Python library for LongPort Open API
Home-Page: https://open.longportapp.com/en/
Requires-Python: >=3.8
Project-URL: changelog, https://github.com/longportapp/openapi/blob/master/python/CHANGELOG.md
Project-URL: documentation, https://open.longportapp.com/en/docs
Project-URL: homepage, https://open.longportapp.com/en/
Project-URL: repository, https://github.com/longportapp/openapi
